{
    "web": {
        "client_id": "652272425650-83dq8p9gtv71rvbgema9ucpejtkmeo00.apps.googleusercontent.com",
        "project_id": "what-is-cloud",
        "auth_uri": "https://accounts.google.com/o/oauth2/auth",
        "token_uri": "https://oauth2.googleapis.com/token",
        "auth_provider_x509_cert_url": "https://www.googleapis.com/oauth2/v1/certs",
        "client_secret": "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",
        "redirect_uris": [
            "https://ambrosiaalert.azurewebsites.net/",
            "https://localhost:7087/"
        ]
    }
}